setup.cfg
setup.py
dataservice/__init__.py
dataservice/config.py
dataservice/ddsclient.py
dataservice.egg-info/PKG-INFO
dataservice.egg-info/SOURCES.txt
dataservice.egg-info/dependency_links.txt
dataservice.egg-info/requires.txt
dataservice.egg-info/top_level.txt
dataservice/core/__init__.py
dataservice/core/ddsapi.py
dataservice/core/download.py
dataservice/core/filedownloader.py
dataservice/core/fileuploader.py
dataservice/core/localstore.py
dataservice/core/parallel.py
dataservice/core/pathfilter.py
dataservice/core/projectuploader.py
dataservice/core/remotestore.py
dataservice/core/upload.py
dataservice/core/util.py