Metadata-Version: 1.1
Name: dataservice
Version: 0.1.0
Summary: Duke Data Service Python Tools
Home-page: https://github.com/benneely/dds
Author: Ben Neely
Author-email: UNKNOWN
License: MIT
Keywords: duke dds dataservice
Platform: UNKNOWN
Classifier: Development Status :: 3 - Alpha
Classifier: Intended Audience :: Developers
Classifier: Intended Audience :: Science/Research
Classifier: Topic :: Utilities
Classifier: License :: OSI Approved :: MIT License
Classifier: Programming Language :: Python :: 2.7
Classifier: Programming Language :: Python :: 3.3
Classifier: Programming Language :: Python :: 3.4
Classifier: Programming Language :: Python :: 3.5
